{
  "$schema": "https://developer.microsoft.com/json-schemas/fabric/item/report/definition/visualContainer/2.10.0/schema.json",
  "name": "00a09497788202eceb22",
  "position": {
    "x": 113.1051051051051,
    "y": 0,
    "z": 0,
    "height": 131.07507507507506,
    "width": 1285.3813813813813,
    "tabOrder": 0
  },
  "visual": {
    "visualType": "cardVisual",
    "query": {
      "queryState": {
        "Data": {
          "projections": [
            {
              "field": {
                "Measure": {
                  "Expression": {
                    "SourceRef": {
                      "Entity": "Metrics"
                    }
                  },
                  "Property": "Sustentantes Total"
                }
              },
              "queryRef": "Encabezado.Sustentantes Total",
              "nativeQueryRef": "Sustentantes Total"
            },
            {
              "field": {
                "Measure": {
                  "Expression": {
                    "SourceRef": {
                      "Entity": "Metrics"
                    }
                  },
                  "Property": "Sustentantes Admitidos Total"
                }
              },
              "queryRef": "Encabezado.Sustentantes Admitidos Total",
              "nativeQueryRef": "Sust. Admitidos",
              "displayName": "Sust. Admitidos"
            },
            {
              "field": {
                "Measure": {
                  "Expression": {
                    "SourceRef": {
                      "Entity": "Metrics"
                    }
                  },
                  "Property": "Pct Ingreso"
                }
              },
              "queryRef": "Encabezado.Pct Ingreso",
              "nativeQueryRef": "Pct Ingreso"
            },
            {
              "field": {
                "Measure": {
                  "Expression": {
                    "SourceRef": {
                      "Entity": "Metrics"
                    }
                  },
                  "Property": "Avg. punto de corte"
                }
              },
              "queryRef": "Encabezado.Avg. punto de corte",
              "nativeQueryRef": "Punto de corte Ceneval",
              "displayName": "Punto de corte Ceneval"
            },
            {
              "field": {
                "Measure": {
                  "Expression": {
                    "SourceRef": {
                      "Entity": "Metrics"
                    }
                  },
                  "Property": "Min Pensamiento Mat Admitido"
                }
              },
              "queryRef": "Contenido.Min Pensamiento Mat Admitido",
              "nativeQueryRef": "Min Pensamiento Mat Admitido"
            },
            {
              "field": {
                "Measure": {
                  "Expression": {
                    "SourceRef": {
                      "Entity": "Metrics"
                    }
                  },
                  "Property": "Avg. Índice Ceneval Admitivo"
                }
              },
              "queryRef": "Contenido.Avg. Índice Ceneval Admitivo",
              "nativeQueryRef": "Avg. Índice Ceneval Admitivo"
            },
            {
              "field": {
                "Measure": {
                  "Expression": {
                    "SourceRef": {
                      "Entity": "Metrics"
                    }
                  },
                  "Property": "Avg. Pensamiento Mat. Admitido"
                }
              },
              "queryRef": "Contenido.Avg. Pensamiento Mat. Admitido",
              "nativeQueryRef": "Avg. Pens. Mat. Admitido",
              "displayName": "Avg. Pens. Mat. Admitido"
            }
          ]
        }
      },
      "sortDefinition": {
        "sort": [
          {
            "field": {
              "Measure": {
                "Expression": {
                  "SourceRef": {
                    "Entity": "Metrics"
                  }
                },
                "Property": "Sustentantes Total"
              }
            },
            "direction": "Descending"
          }
        ],
        "isDefaultSort": true
      }
    },
    "objects": {
      "shapeCustomRectangle": [
        {
          "properties": {
            "tileShape": {
              "expr": {
                "Literal": {
                  "Value": "'tabCutTopCorners'"
                }
              }
            },
            "rectangleRoundedCurve": {
              "expr": {
                "Literal": {
                  "Value": "11L"
                }
              }
            },
            "rectangleRoundedCurveCustomStyle": {
              "expr": {
                "Literal": {
                  "Value": "false"
                }
              }
            },
            "tabCutCornerSnipSizeCustomStyle": {
              "expr": {
                "Literal": {
                  "Value": "true"
                }
              }
            },
            "tabCutCornerSnipSizeLeftTop": {
              "expr": {
                "Literal": {
                  "Value": "25L"
                }
              }
            },
            "tabCutCornerSnipSizeRightBottom": {
              "expr": {
                "Literal": {
                  "Value": "25L"
                }
              }
            }
          },
          "selector": {
            "id": "default"
          }
        }
      ],
      "accentBar": [
        {
          "properties": {
            "show": {
              "expr": {
                "Literal": {
                  "Value": "true"
                }
              }
            }
          }
        },
        {
          "properties": {
            "width": {
              "expr": {
                "Literal": {
                  "Value": "11L"
                }
              }
            },
            "color": {
              "solid": {
                "color": {
                  "expr": {
                    "ThemeDataColor": {
                      "ColorId": 8,
                      "Percent": 0
                    }
                  }
                }
              }
            }
          },
          "selector": {
            "id": "default"
          }
        },
        {
          "properties": {
            "color": {
              "solid": {
                "color": {
                  "expr": {
                    "Literal": {
                      "Value": "'#1E2159'"
                    }
                  }
                }
              }
            }
          },
          "selector": {
            "metadata": "Encabezado.Sustentantes Admitidos Total"
          }
        },
        {
          "properties": {
            "color": {
              "solid": {
                "color": {
                  "expr": {
                    "Literal": {
                      "Value": "'#A68521'"
                    }
                  }
                }
              }
            }
          },
          "selector": {
            "metadata": "Encabezado.Pct Ingreso"
          }
        },
        {
          "properties": {
            "color": {
              "solid": {
                "color": {
                  "expr": {
                    "Literal": {
                      "Value": "'#A68521'"
                    }
                  }
                }
              }
            }
          },
          "selector": {
            "metadata": "Encabezado.Avg. punto de corte"
          }
        },
        {
          "properties": {
            "color": {
              "solid": {
                "color": {
                  "expr": {
                    "Literal": {
                      "Value": "'#A68521'"
                    }
                  }
                }
              }
            }
          },
          "selector": {
            "metadata": "Contenido.Avg. Índice Ceneval Admitivo"
          }
        },
        {
          "properties": {
            "color": {
              "solid": {
                "color": {
                  "expr": {
                    "Literal": {
                      "Value": "'#A68521'"
                    }
                  }
                }
              }
            }
          },
          "selector": {
            "metadata": "Contenido.Avg. Pensamiento Mat. Admitido"
          }
        },
        {
          "properties": {
            "color": {
              "solid": {
                "color": {
                  "expr": {
                    "Literal": {
                      "Value": "'#A68521'"
                    }
                  }
                }
              }
            }
          },
          "selector": {
            "metadata": "Contenido.Min Pensamiento Mat Admitido"
          }
        },
        {
          "properties": {
            "color": {
              "solid": {
                "color": {
                  "expr": {
                    "Literal": {
                      "Value": "'#1E2159'"
                    }
                  }
                }
              }
            }
          },
          "selector": {
            "metadata": "Encabezado.Sustentantes Total"
          }
        }
      ],
      "value": [
        {
          "properties": {
            "fontSize": {
              "expr": {
                "Literal": {
                  "Value": "14D"
                }
              }
            },
            "horizontalAlignment": {
              "expr": {
                "Literal": {
                  "Value": "'center'"
                }
              }
            },
            "labelDisplayUnits": {
              "expr": {
                "Literal": {
                  "Value": "1D"
                }
              }
            }
          },
          "selector": {
            "id": "default"
          }
        },
        {
          "properties": {
            "fontColor": {
              "solid": {
                "color": {
                  "expr": {
                    "Literal": {
                      "Value": "'#1E2159'"
                    }
                  }
                }
              }
            }
          },
          "selector": {
            "metadata": "Encabezado.Sustentantes Admitidos Total"
          }
        },
        {
          "properties": {
            "fontColor": {
              "solid": {
                "color": {
                  "expr": {
                    "Literal": {
                      "Value": "'#A68521'"
                    }
                  }
                }
              }
            }
          },
          "selector": {
            "metadata": "Encabezado.Pct Ingreso"
          }
        },
        {
          "properties": {
            "fontColor": {
              "solid": {
                "color": {
                  "expr": {
                    "Literal": {
                      "Value": "'#A68521'"
                    }
                  }
                }
              }
            },
            "fontSize": {
              "expr": {
                "Literal": {
                  "Value": "14D"
                }
              }
            }
          },
          "selector": {
            "metadata": "Encabezado.Avg. punto de corte"
          }
        },
        {
          "properties": {
            "fontColor": {
              "solid": {
                "color": {
                  "expr": {
                    "Literal": {
                      "Value": "'#A68521'"
                    }
                  }
                }
              }
            }
          },
          "selector": {
            "metadata": "Contenido.Avg. Índice Ceneval Admitivo"
          }
        },
        {
          "properties": {
            "fontColor": {
              "solid": {
                "color": {
                  "expr": {
                    "Literal": {
                      "Value": "'#A68521'"
                    }
                  }
                }
              }
            }
          },
          "selector": {
            "metadata": "Contenido.Avg. Pensamiento Mat. Admitido"
          }
        },
        {
          "properties": {
            "fontColor": {
              "solid": {
                "color": {
                  "expr": {
                    "Literal": {
                      "Value": "'#A68521'"
                    }
                  }
                }
              }
            }
          },
          "selector": {
            "metadata": "Contenido.Min Pensamiento Mat Admitido"
          }
        },
        {
          "properties": {
            "fontColor": {
              "solid": {
                "color": {
                  "expr": {
                    "Literal": {
                      "Value": "'#1E2159'"
                    }
                  }
                }
              }
            }
          },
          "selector": {
            "metadata": "Encabezado.Sustentantes Total"
          }
        }
      ],
      "label": [
        {
          "properties": {
            "fontFamily": {
              "expr": {
                "Literal": {
                  "Value": "'wf_standard-font, helvetica, arial, sans-serif'"
                }
              }
            },
            "fontSize": {
              "expr": {
                "Literal": {
                  "Value": "8D"
                }
              }
            }
          },
          "selector": {
            "id": "default"
          }
        },
        {
          "properties": {
            "fontColor": {
              "solid": {
                "color": {
                  "expr": {
                    "Literal": {
                      "Value": "'#1E2159'"
                    }
                  }
                }
              }
            },
            "fontSize": {
              "expr": {
                "Literal": {
                  "Value": "10D"
                }
              }
            }
          },
          "selector": {
            "metadata": "Encabezado.Sustentantes Admitidos Total"
          }
        },
        {
          "properties": {
            "fontColor": {
              "solid": {
                "color": {
                  "expr": {
                    "Literal": {
                      "Value": "'#A68521'"
                    }
                  }
                }
              }
            },
            "fontSize": {
              "expr": {
                "Literal": {
                  "Value": "12D"
                }
              }
            }
          },
          "selector": {
            "metadata": "Encabezado.Pct Ingreso"
          }
        },
        {
          "properties": {
            "fontSize": {
              "expr": {
                "Literal": {
                  "Value": "9D"
                }
              }
            },
            "fontColor": {
              "solid": {
                "color": {
                  "expr": {
                    "Literal": {
                      "Value": "'#A68521'"
                    }
                  }
                }
              }
            }
          },
          "selector": {
            "metadata": "Encabezado.Avg. punto de corte"
          }
        },
        {
          "properties": {
            "fontSize": {
              "expr": {
                "Literal": {
                  "Value": "8D"
                }
              }
            },
            "fontColor": {
              "solid": {
                "color": {
                  "expr": {
                    "Literal": {
                      "Value": "'#A68521'"
                    }
                  }
                }
              }
            }
          },
          "selector": {
            "metadata": "Contenido.Avg. Índice Ceneval Admitivo"
          }
        },
        {
          "properties": {
            "fontColor": {
              "solid": {
                "color": {
                  "expr": {
                    "Literal": {
                      "Value": "'#A68521'"
                    }
                  }
                }
              }
            }
          },
          "selector": {
            "metadata": "Contenido.Avg. Pensamiento Mat. Admitido"
          }
        },
        {
          "properties": {
            "fontColor": {
              "solid": {
                "color": {
                  "expr": {
                    "Literal": {
                      "Value": "'#A68521'"
                    }
                  }
                }
              }
            }
          },
          "selector": {
            "metadata": "Contenido.Min Pensamiento Mat Admitido"
          }
        }
      ],
      "spacing": [
        {
          "properties": {
            "verticalSpacing": {
              "expr": {
                "Literal": {
                  "Value": "8L"
                }
              }
            }
          },
          "selector": {
            "id": "default"
          }
        }
      ],
      "layout": [
        {
          "properties": {
            "cellPadding": {
              "expr": {
                "Literal": {
                  "Value": "3L"
                }
              }
            }
          }
        }
      ]
    },
    "visualContainerObjects": {
      "padding": [
        {
          "properties": {
            "left": {
              "expr": {
                "Literal": {
                  "Value": "10D"
                }
              }
            },
            "top": {
              "expr": {
                "Literal": {
                  "Value": "10D"
                }
              }
            },
            "bottom": {
              "expr": {
                "Literal": {
                  "Value": "10D"
                }
              }
            },
            "right": {
              "expr": {
                "Literal": {
                  "Value": "10D"
                }
              }
            }
          }
        }
      ],
      "title": [
        {
          "properties": {
            "show": {
              "expr": {
                "Literal": {
                  "Value": "true"
                }
              }
            },
            "text": {
              "expr": {
                "Measure": {
                  "Expression": {
                    "SourceRef": {
                      "Entity": "Metrics"
                    }
                  },
                  "Property": "Título"
                }
              }
            },
            "fontSize": {
              "expr": {
                "Literal": {
                  "Value": "10D"
                }
              }
            }
          }
        }
      ],
      "visualTooltip": [
        {
          "properties": {
            "show": {
              "expr": {
                "Literal": {
                  "Value": "true"
                }
              }
            }
          }
        }
      ]
    },
    "drillFilterOtherVisuals": true
  }
}